Perceptron/__init__.py
Perceptron/perceptron.py
Perceptron/utils.py
Percptron_rohandhanraj-0.0.5.dist-info/LICENSE
Percptron_rohandhanraj-0.0.5.dist-info/METADATA
Percptron_rohandhanraj-0.0.5.dist-info/WHEEL
Percptron_rohandhanraj-0.0.5.dist-info/top_level.txt
Percptron_rohandhanraj-0.0.5.dist-info/RECORD
