Metadata-Version: 2.1
Name: Percptron-rohandhanraj
Version: 0.0.5
Summary: Its an Implementation of Percptron
Home-page: https://github.com/rohandhanraj/Percptron
Author: rohandhanraj
Author-email: rdy5674@gmail.com
License: UNKNOWN
Project-URL: Bug Tracker, https://github.com/rohandhanraj/Percptron/issues
Platform: UNKNOWN
Classifier: Programming Language :: Python :: 3
Classifier: License :: OSI Approved :: MIT License
Classifier: Operating System :: OS Independent
Requires-Python: >=3.7
License-File: LICENSE
Requires-Dist: numpy
Requires-Dist: tqdm
